Assignment_2/prob_3/8to1_mux.v
module mux_8to1(
    input [7:0] in,     // 8-bit input for 8 data lines
    input [2:0] sel,    // 3-bit select input
    output reg out      // single output
);

always @(*) begin
    case (sel)
        3'b000: out = in[0];
        3'b001: out = in[1];
        3'b010: out = in[2];
        3'b011: out = in[3];
        3'b100: out = in[4];
        3'b101: out = in[5];
        3'b110: out = in[6];
        3'b111: out = in[7];
        default: out = 1'b0; // default case
    endcase
end

endmodule

Assignment_2/prob_3/testbench.v
module tb_mux_8to1;

    // Testbench variables
    reg [7:0] in;       // 8-bit input for the 8-to-1 multiplexer
    reg [2:0] sel;      // 3-bit selection line
    wire out;           // Output of the multiplexer

    // Instantiate the 8-to-1 multiplexer
    mux_8to1 uut (
        .in(in),
        .sel(sel),
        .out(out)
    );

    // Testbench initial block
    initial begin
        // Monitor changes
        $monitor("Time = %0t | in = %b | sel = %b | out = %b", $time, in, sel, out);
        
        // Test case 1: sel = 3'b000, in[0] should be selected
        in = 8'b10101010;
        sel = 3'b000;
        #10;
        
        // Test case 2: sel = 3'b001, in[1] should be selected
        sel = 3'b001;
        #10;
        
        // Test case 3: sel = 3'b010, in[2] should be selected
        sel = 3'b010;
        #10;
        
        // Test case 4: sel = 3'b011, in[3] should be selected
        sel = 3'b011;
        #10;
        
        // Test case 5: sel = 3'b100, in[4] should be selected
        sel = 3'b100;
        #10;
        
        // Test case 6: sel = 3'b101, in[5] should be selected
        sel = 3'b101;
        #10;
        
        // Test case 7: sel = 3'b110, in[6] should be selected
        sel = 3'b110;
        #10;
        
        // Test case 8: sel = 3'b111, in[7] should be selected
        sel = 3'b111;
        #10;
        
        // End the simulation
        $finish;
    end

    initial begin
        // Dump the waveforms
        $dumpfile("tb_mux_8to1.vcd");
        $dumpvars(0);
    end

endmodule

Assignment_2/prob_3/tb_mux_8to1.vcd
$date
	Fri Sep 27 18:32:00 2024
$end
$version
	Icarus Verilog
$end
$timescale
	1s
$end
$scope module tb_mux_8to1 $end
$var wire 1 ! out $end
$var reg 8 " in [7:0] $end
$var reg 3 # sel [2:0] $end
$scope module uut $end
$var wire 8 $ in [7:0] $end
$var wire 3 % sel [2:0] $end
$var reg 1 ! out $end
$upscope $end
$upscope $end
$enddefinitions $end
#0
$dumpvars
b0 %
b10101010 $
b0 #
b10101010 "
0!
$end
#10
1!
b1 #
b1 %
#20
0!
b10 #
b10 %
#30
1!
b11 #
b11 %
#40
0!
b100 #
b100 %
#50
1!
b101 #
b101 %
#60
0!
b110 #
b110 %
#70
1!
b111 #
b111 %
