Assignment_4/prob_3/fsm.v
module sequence_detector (
    input wire clk,      // Clock signal
    input wire reset,    // Reset signal (active high)
    input wire x,        // Input variable
    output reg Z         // Output variable
);

    // State encoding using local parameters
    localparam [2:0]
        S0 = 3'b000,     // Initial state
        S1 = 3'b001,     // Detected '1'
        S2 = 3'b010,     // Detected '11'
        S3 = 3'b011,     // Detected '110'
        S4 = 3'b100;     // Detected '1101' (sequence complete)

    reg [2:0] current_state, next_state;

    // Sequential logic for state transitions
    always @(posedge clk or posedge reset) begin
        if (reset)
            current_state <= S0;   // Reset to initial state
        else
            current_state <= next_state;
    end

    // Combinational logic for next state and output
    always @(*) begin
        // Default assignments
        next_state = current_state;
        Z = 1'b0;  // Default output

        case (current_state)
            S0: begin
                if (x)
                    next_state = S1;
                else
                    next_state = S0;
            end

            S1: begin
                if (x)
                    next_state = S2;
                else
                    next_state = S0;
            end

            S2: begin
                if (x)
                    next_state = S2;  // Stay in S2 if input is '1'
                else
                    next_state = S3;
            end

            S3: begin
                if (x)
                    next_state = S4;
                else
                    next_state = S0;
            end

            S4: begin
                Z = 1'b1;  // Output '1' when sequence '1101' is detected
                if (x)
                    next_state = S2;  // Overlapping sequence
                else
                    next_state = S0;
            end

            default: begin
                next_state = S0;
            end
        endcase
    end

endmodule

module tb_sequence_detector;
    reg clk;
    reg reset;
    reg x;
    wire Z;

    // Instantiate the sequence detector
    sequence_detector uut (
        .clk(clk),
        .reset(reset),
        .x(x),
        .Z(Z)
    );

    // Clock generation: 10ns period
    always #5 clk = ~clk;

    // Apply test sequences
    initial begin
        // Initialize inputs
        clk = 0;
        reset = 1;
        x = 0;

        // Apply reset
        #10 reset = 0;

        // First test sequence: 1 1 0 1 (should detect and set Z high)
        #10 x = 1;  // Time 10ns
        #10 x = 1;  // Time 20ns
        #10 x = 0;  // Time 30ns
        #10 x = 1;  // Time 40ns, Z should be set to 1 here

        // Test overlapping sequences: immediately start new detection
        #10 x = 1;  // Time 50ns
        #10 x = 1;  // Time 60ns
        #10 x = 0;  // Time 70ns
        #10 x = 1;  // Time 80ns, Z should be set to 1 again

        // Test with non-matching bits
        #10 x = 0;  // Time 90ns
        #10 x = 1;  // Time 100ns
        #10 x = 0;  // Time 110ns
        #10 x = 0;  // Time 120ns
        #10 x = 1;  // Time 130ns, Z should remain 0

        // Finish simulation
        #50 $stop;
    end

    // Monitor signals
    initial begin
        $monitor("Time=%0t | x=%b | Z=%b | State=%b", $time, x, Z, uut.current_state);
    end

    // Generate waveform file (optional)
    initial begin
        $dumpfile("sequence_detector.vcd");
        $dumpvars(0, tb_sequence_detector);
    end

endmodule

Assignment_4/prob_3/sequence_detector.vcd
$date
	Fri Sep 27 23:37:28 2024
$end
$version
	Icarus Verilog
$end
$timescale
	1s
$end
$scope module tb_sequence_detector $end
$var wire 1 ! Z $end
$var reg 1 " clk $end
$var reg 1 # reset $end
$var reg 1 $ x $end
$scope module uut $end
$var wire 1 " clk $end
$var wire 1 # reset $end
$var wire 1 $ x $end
$var reg 1 ! Z $end
$var reg 3 % current_state [2:0] $end
$var reg 3 & next_state [2:0] $end
$upscope $end
$upscope $end
$enddefinitions $end
#0
$dumpvars
b0 &
b0 %
0$
1#
0"
0!
$end
#5
1"
#10
0"
0#
#15
1"
#20
b1 &
0"
1$
#25
b10 &
b1 %
1"
#30
0"
#35
b10 %
1"
#40
b11 &
0"
0$
#45
b0 &
b11 %
1"
#50
b100 &
0"
1$
#55
b10 &
1!
b100 %
1"
#60
0"
#65
0!
b10 %
1"
#70
0"
#75
1"
#80
b11 &
0"
0$
#85
b0 &
b11 %
1"
#90
b100 &
0"
1$
#95
b10 &
1!
b100 %
1"
#100
1!
b0 &
0"
0$
#105
0!
b0 %
1"
#110
b1 &
0"
1$
#115
b10 &
b1 %
1"
#120
b0 &
0"
0$
#125
b0 %
1"
#130
0"
#135
1"
#140
b1 &
0"
1$
#145
b10 &
b1 %
1"
#150
0"
#155
b10 %
1"
