Assignment_4/prob_2/mealy.v
module mealy_machine (
    input wire clk,       // Clock signal
    input wire reset,     // Reset signal (active high)
    input wire in,        // Single-bit input
    output reg out        // Single-bit output
);

    // State encoding using local parameters
    localparam [2:0]
        S0 = 3'b000,  // Initial state
        S1 = 3'b001,  // Detected '1'
        S2 = 3'b010,  // Detected '10'
        S3 = 3'b011;  // Detected '101'

    reg [2:0] current_state, next_state;

    // Sequential logic for state transitions
    always @(posedge clk or posedge reset) begin
        if (reset)
            current_state <= S0;  // Reset to initial state
        else
            current_state <= next_state;
    end

    // Combinational logic for next state and output
    always @(*) begin
        // Default assignments
        next_state = current_state;
        out = 1'b0;

        case (current_state)
            S0: begin
                if (in) begin
                    next_state = S1;
                end else begin
                    next_state = S0;
                end
            end

            S1: begin
                if (~in) begin
                    next_state = S2;
                end else begin
                    next_state = S1;
                end
            end

            S2: begin
                if (in) begin
                    next_state = S3;
                end else begin
                    next_state = S0;
                end
            end

            S3: begin
                if (in) begin
                    out = 1'b1;       // Output high immediately upon receiving '1'
                    next_state = S1;  // Prepare for potential overlapping sequences
                end else begin
                    next_state = S2;
                end
            end

            default: begin
                next_state = S0;
            end
        endcase
    end

endmodule

module tb_mealy_machine;
    reg clk;
    reg reset;
    reg in;
    wire out;

    // Instantiate the Mealy machine
    mealy_machine uut (
        .clk(clk),
        .reset(reset),
        .in(in),
        .out(out)
    );

    // Clock generation: 10ns period
    always #5 clk = ~clk;

    // Apply test sequences
    initial begin
        // Initialize inputs
        clk = 0;
        reset = 1;
        in = 0;

        // Apply reset
        #10 reset = 0;

        // Test sequence: 1 0 1 1 (should detect and set output high at last '1')
        #10 in = 1;  // Time 10ns
        #10 in = 0;  // Time 20ns
        #10 in = 1;  // Time 30ns
        #10 in = 1;  // Time 40ns, output should go high here

        // Hold input and observe output
        #10 in = 0;  // Time 50ns
        #10 in = 1;  // Time 60ns

        // Test overlapping sequences
        #10 in = 0;  // Time 70ns
        #10 in = 1;  // Time 80ns
        #10 in = 1;  // Time 90ns, output should go high here again

        // Finish simulation
        #20 $stop;
    end

    // Monitor signals
    initial begin
        $monitor("Time=%0t | clk=%b | reset=%b | in=%b | out=%b | state=%b",
                 $time, clk, reset, in, out, uut.current_state);
    end

    // Generate waveform file
    initial begin
        $dumpfile("mealy_machine.vcd");
        $dumpvars(0, tb_mealy_machine);
    end

endmodule

Assignment_4/prob_2/mealy_machine.vcd
$date
	Fri Sep 27 23:32:10 2024
$end
$version
	Icarus Verilog
$end
$timescale
	1s
$end
$scope module tb_mealy_machine $end
$var wire 1 ! out $end
$var reg 1 " clk $end
$var reg 1 # in $end
$var reg 1 $ reset $end
$scope module uut $end
$var wire 1 " clk $end
$var wire 1 # in $end
$var wire 1 $ reset $end
$var reg 3 % current_state [2:0] $end
$var reg 3 & next_state [2:0] $end
$var reg 1 ! out $end
$upscope $end
$upscope $end
$enddefinitions $end
#0
$dumpvars
b0 &
b0 %
1$
0#
0"
0!
$end
#5
1"
#10
0"
0$
#15
1"
#20
b1 &
0"
1#
#25
b1 %
1"
#30
b10 &
0"
0#
#35
b0 &
b10 %
1"
#40
b11 &
0"
1#
#45
b1 &
1!
b11 %
1"
#50
0"
#55
0!
b1 %
1"
#60
b10 &
0"
0#
#65
b0 &
b10 %
1"
#70
b11 &
0"
1#
#75
b1 &
1!
b11 %
1"
#80
0!
b10 &
0"
0#
#85
b0 &
b10 %
1"
#90
b11 &
0"
1#
#95
b1 &
1!
b11 %
1"
#100
0"
#105
0!
b1 %
1"
