Assignment_3/prob_4/gray.v
module gray_up_down_counter (
    input wire clk,          // Clock input
    input wire reset,        // Asynchronous reset
    input wire up,           // UP control signal
    output reg [2:0] gray_code // 3-bit Gray Code output
);

    // Internal variable to track binary counter value (0 to 7)
    reg [2:0] binary_counter;

    // Gray code generation function (convert binary to Gray code)
    function [2:0] binary_to_gray;
        input [2:0] binary_value;
        begin
            binary_to_gray = binary_value ^ (binary_value >> 1);
        end
    endfunction

    // Always block triggered by clock or reset
    always @(posedge clk or posedge reset) begin
        if (reset) begin
            // Reset the binary counter and Gray code to 0
            binary_counter <= 3'b000;
            gray_code <= 3'b000;
        end else if (up) begin
            // Increment binary counter and convert to Gray code
            if (binary_counter == 3'b111) // If the counter reaches 7
                binary_counter <= 3'b000; // Wrap around to 0
            else
                binary_counter <= binary_counter + 1;
                
            // Convert binary counter to Gray code
            gray_code <= binary_to_gray(binary_counter);
        end
    end
endmodule

Assignment_3/prob_4/testbench.v
module tb_gray_up_down_counter;

    reg clk;               // Clock signal
    reg reset;             // Asynchronous reset signal
    reg up;                // UP control signal (when 1, the counter advances)
    wire [2:0] gray_code;  // 3-bit Gray code output

    // Instantiate the gray_up_down_counter module
    gray_up_down_counter uut (
        .clk(clk),
        .reset(reset),
        .up(up),
        .gray_code(gray_code)
    );

    // Clock generation: Toggle clock every 5 time units to simulate a clock signal
    always begin
        #5 clk = ~clk;   // 50% duty cycle clock
    end

    initial begin
        // Initialize the signals
        clk = 0;
        reset = 0;
        up = 0;

        // Apply a reset for 10 time units
        #10 reset = 1;   // Assert reset
        #10 reset = 0;   // Deassert reset

        // Test Case 1: UP = 1 (counting mode)
        up = 1;
        #80;  // Let the counter run for 8 clock cycles

        // Test Case 2: UP = 0 (hold the current value)
        up = 0;
        #30;  // Hold the counter value for 3 clock cycles

        // Test Case 3: UP = 1 (resume counting mode)
        up = 1;
        #50;  // Let the counter run for 5 clock cycles

        // End the simulation after all test cases
        $finish;
    end

    // Monitor the signals and output
    initial begin
        $monitor("Time = %0t | Reset = %b | UP = %b | Gray Code = %b", $time, reset, up, gray_code);
    end

    // Dump waveform for debugging (view in waveform viewer)
    initial begin
        $dumpfile("tb_gray_up_down_counter.vcd");  // Specify VCD file name
        $dumpvars(0, tb_gray_up_down_counter);     // Dump all variables for this module
    end

endmodule

Assignment_3/prob_4/tb_gray_up_down_counter.vcd
$date
	Fri Sep 27 22:49:16 2024
$end
$version
	Icarus Verilog
$end
$timescale
	1s
$end
$scope module tb_gray_up_down_counter $end
$var wire 3 ! gray_code [2:0] $end
$var reg 1 " clk $end
$var reg 1 # reset $end
$var reg 1 $ up $end
$scope module uut $end
$var wire 1 " clk $end
$var wire 1 # reset $end
$var wire 1 $ up $end
$var reg 3 % binary_counter [2:0] $end
$var reg 3 & gray_code [2:0] $end
$scope function binary_to_gray $end
$var reg 3 ' binary_value [2:0] $end
$upscope $end
$upscope $end
$upscope $end
$enddefinitions $end
#0
$dumpvars
bx '
bx &
bx %
0$
0#
0"
bx !
$end
#5
1"
#10
b0 !
b0 &
b0 %
0"
1#
#15
1"
#20
0"
1$
0#
#25
b1 %
b0 '
1"
#30
0"
#35
b1 !
b1 &
b10 %
b1 '
1"
#40
0"
#45
b11 !
b11 &
b11 %
b10 '
1"
#50
0"
#55
b10 !
b10 &
b100 %
b11 '
1"
#60
0"
#65
b110 !
b110 &
b101 %
b100 '
1"
#70
0"
#75
b111 !
b111 &
b110 %
b101 '
1"
#80
0"
#85
b101 !
b101 &
b111 %
b110 '
1"
#90
0"
#95
b100 !
b100 &
b0 %
b111 '
1"
#100
0"
0$
#105
1"
#110
0"
#115
1"
#120
0"
#125
1"
#130
0"
1$
#135
b0 !
b0 &
b1 %
b0 '
1"
#140
0"
#145
b1 !
b1 &
b10 %
b1 '
1"
#150
0"
#155
b11 !
b11 &
b11 %
b10 '
1"
#160
0"
#165
b10 !
b10 &
b100 %
b11 '
1"
#170
0"
#175
b110 !
b110 &
b101 %
b100 '
1"
