Assignment_3/prob_3/counter.v
module down_counter (
    input wire clk,      
    input wire reset,    
    output reg [2:0] count 
);

    // Always block triggered by the positive edge of the clock or reset
    always @(posedge clk or posedge reset) begin
        if (reset) begin
            count <= 3'b111; // Reset the count to 7 (binary 111)
        end
        else begin
            if (count == 3'b000) // If the count reaches 0
                count <= 3'b111; // Reset back to 7
            else
                count <= count - 1'b1; // Decrement the count
        end
    end
endmodule

Assignment_3/prob_3/testbench.v
module tb_down_counter;

    reg clk;
    reg reset;
    wire [2:0] count;

    // Instantiate the down_counter module
    down_counter uut (
        .clk(clk),
        .reset(reset),
        .count(count)
    );

    // Clock generation (50% duty cycle)
    always begin
        #5 clk = ~clk; // Toggle clock every 5 time units
    end

    initial begin
        // Initialize signals
        clk = 0;
        reset = 0;

        // Apply reset for a short period
        #10 reset = 1;   // Assert reset
        #10 reset = 0;   // Deassert reset

        // Let the counter run for 100 time units
        #100;

        // End simulation
        $finish;
    end

    // Monitor the output
    initial begin
        $monitor("Time = %0t | Reset = %b | Count = %b", $time, reset, count);
    end

    // Dump the waveforms for debugging
    initial begin
        $dumpfile("tb_down_counter.vcd");
        $dumpvars(0, tb_down_counter);
    end

endmodule

Assignment_3/prob_3/tb_down_counter.vcd
$date
	Fri Sep 27 21:50:00 2024
$end
$version
	Icarus Verilog
$end
$timescale
	1s
$end
$scope module tb_down_counter $end
$var wire 3 ! count [2:0] $end
$var reg 1 " clk $end
$var reg 1 # reset $end
$scope module uut $end
$var wire 1 " clk $end
$var wire 1 # reset $end
$var reg 3 $ count [2:0] $end
$upscope $end
$upscope $end
$enddefinitions $end
#0
$dumpvars
bx $
0#
0"
bx !
$end
#5
1"
#10
b111 !
b111 $
0"
1#
#15
1"
#20
0"
0#
#25
b110 !
b110 $
1"
#30
0"
#35
b101 !
b101 $
1"
#40
0"
#45
b100 !
b100 $
1"
#50
0"
#55
b11 !
b11 $
1"
#60
0"
#65
b10 !
b10 $
1"
#70
0"
#75
b1 !
b1 $
1"
#80
0"
#85
b0 !
b0 $
1"
#90
0"
#95
b111 !
b111 $
1"
#100
0"
#105
b110 !
b110 $
1"
#110
0"
#115
b101 !
b101 $
1"
